core_evals/simple_evals/__init__.py
core_evals/simple_evals/framework.yml
core_evals/simple_evals/framework_entrypoint.py
core_evals/simple_evals/output.py
simple_evals/__init__.py
simple_evals/__main__.py
simple_evals/common.py
simple_evals/constants.py
simple_evals/diskcaching.py
simple_evals/seed_generator.py
simple_evals/simple_evals_types.py
simple_evals/configs/README.md
simple_evals/configs/example_comprehensive.yml
simple_evals/configs/judge/gpt4.yaml
simple_evals/configs/judge/llama70b.yaml
simple_evals/configs/regex/aa_boxed.regex
simple_evals/configs/tasks/AA_AIME_2024.yml
simple_evals/configs/tasks/AA_math_test_500.yml
simple_evals/configs/tasks/AIME_2025.yml
simple_evals/configs/tasks/aime_2024_nemo.yml
simple_evals/configs/tasks/aime_2025_nemo.yml
simple_evals/configs/tasks/math_test_500_nemo.yml
simple_evals/configs/templates/aa_boxed.template
simple_evals/configs/templates/nemo_math.template
simple_evals/custom_parametrization/__init__.py
simple_evals/custom_parametrization/config_loader.py
simple_evals/custom_parametrization/extractors.py
simple_evals/custom_parametrization/scorers.py
simple_evals/evals/__init__.py
simple_evals/evals/browsecomp_eval.py
simple_evals/evals/drop_eval.py
simple_evals/evals/gpqa_eval.py
simple_evals/evals/healthbench_eval.py
simple_evals/evals/humaneval_eval.py
simple_evals/evals/math_eval.py
simple_evals/evals/mgsm_eval.py
simple_evals/evals/mmlu_eval.py
simple_evals/evals/mmlu_pro_eval.py
simple_evals/evals/simpleqa_eval.py
simple_evals/evals/human_eval/__init__.py
simple_evals/evals/human_eval/data.py
simple_evals/evals/human_eval/evaluate_functional_correctness.py
simple_evals/evals/human_eval/evaluation.py
simple_evals/evals/human_eval/execution.py
simple_evals/evals/math_grading/__init__.py
simple_evals/evals/math_grading/math_normalize.py
simple_evals/evals/math_grading/nemo_grader.py
simple_evals/evals/math_grading/sympy_grader.py
simple_evals/sampler/__init__.py
simple_evals/sampler/chat_completion_sampler.py
nvidia_simple_evals-25.11.dist-info/METADATA
nvidia_simple_evals-25.11.dist-info/WHEEL
nvidia_simple_evals-25.11.dist-info/entry_points.txt
nvidia_simple_evals-25.11.dist-info/licenses/LICENSE
nvidia_simple_evals-25.11.dist-info/RECORD
