Metadata-Version: 2.4
Name: nvidia_simple_evals
Version: 25.11
Summary: Open AI simple evals - packaged by NVIDIA
License: MIT
License-File: LICENSE
Classifier: Development Status :: 5 - Production/Stable
Classifier: License :: OSI Approved :: MIT License
Classifier: Operating System :: OS Independent
Classifier: Programming Language :: Python :: 3
Requires-Python: >=3.8
Requires-Dist: aiohttp>=3.11.11
Requires-Dist: blobfile>=3.0.0
Requires-Dist: datasets>=3.2.0
Requires-Dist: jinja2>=3.1.5
Requires-Dist: nemo-evaluator
Requires-Dist: openai>=1.59.6
Requires-Dist: pandas>=2.2.3
Requires-Dist: pylatexenc>=2.10.0
Requires-Dist: scipy>=1.15.0
Requires-Dist: sympy>=1.13.3
Requires-Dist: tabulate>=0.9.0
Requires-Dist: tenacity==9.0.0
Requires-Dist: tqdm>=4.67.1
